{"feed_title": "Releases - Apple Developer", "feed_link": "https://developer.apple.com/news/", "entries": [{"title": "iOS 17.5 beta 2 (21F5058e)", "link": "https://developer.apple.com/news/releases/?id=04162024c", "published": "Tue, 16 Apr 2024 10:00:00 PDT"}, {"title": "iPadOS 17.5 beta 2 (21F5058e)", "link": "https://developer.apple.com/news/releases/?id=04162024g", "published": "Tue, 16 Apr 2024 10:00:00 PDT"}, {"title": "macOS 14.5 beta 2 (23F5059e)", "link": "https://developer.apple.com/news/releases/?id=04162024e", "published": "Tue, 16 Apr 2024 10:00:00 PDT"}, {"title": "tvOS 17.5 beta 2 (21L5553e)", "link": "https://developer.apple.com/news/releases/?id=04162024d", "published": "Tue, 16 Apr 2024 10:00:00 PDT"}, {"title": "visionOS 1.2 beta 2 (21O5565d)", "link": "https://developer.apple.com/news/releases/?id=04162024f", "published": "Tue, 16 Apr 2024 10:00:00 PDT"}, {"title": "watchOS 10.5 beta 2 (21T5555d)", "link": "https://developer.apple.com/news/releases/?id=04162024h", "published": "Tue, 16 Apr 2024 10:00:00 PDT"}, {"title": "visionOS 1.2 beta (21O5555f)", "link": "https://developer.apple.com/news/releases/?id=04092024b", "published": "Tue, 09 Apr 2024 10:00:00 PDT"}, {"title": "visionOS 1.1.2 (21O231)", "link": "https://developer.apple.com/news/releases/?id=04092024a", "published": "Tue, 09 Apr 2024 10:00:00 PDT"}, {"title": "iOS 17.5 beta (21F5048f)", "link": "https://developer.apple.com/news/releases/?id=04022024f", "published": "Tue, 02 Apr 2024 10:00:00 PDT"}, {"title": "iPadOS 17.5 beta (21F5048f)", "link": "https://developer.apple.com/news/releases/?id=04022024e", "published": "Tue, 02 Apr 2024 10:00:00 PDT"}, {"title": "macOS 14.5 beta (23F5049f)", "link": "https://developer.apple.com/news/releases/?id=04022024d", "published": "Tue, 02 Apr 2024 10:00:00 PDT"}, {"title": "tvOS 17.5 beta (21L5543d)", "link": "https://developer.apple.com/news/releases/?id=04022024c", "published": "Tue, 02 Apr 2024 10:00:00 PDT"}, {"title": "watchOS 10.5 beta (21T5545f)", "link": "https://developer.apple.com/news/releases/?id=04022024a", "published": "Tue, 02 Apr 2024 10:00:00 PDT"}, {"title": "iOS 17.4.1 (21E237)", "link": "https://developer.apple.com/news/releases/?id=03272024b", "published": "Wed, 27 Mar 2024 10:00:00 PDT"}, {"title": "iPadOS 17.4.1 (21E237)", "link": "https://developer.apple.com/news/releases/?id=03272024a", "published": "Wed, 27 Mar 2024 10:00:00 PDT"}, {"title": "macOS 14.4.1 (23E224)", "link": "https://developer.apple.com/news/releases/?id=03252024a", "published": "Mon, 25 Mar 2024 10:00:00 PDT"}, {"title": "iOS 16.7.7 (20H330)", "link": "https://developer.apple.com/news/releases/?id=03212024b", "published": "Thu, 21 Mar 2024 10:00:00 PDT"}, {"title": "iPadOS 16.7.7 (20H330)", "link": "https://developer.apple.com/news/releases/?id=03212024a", "published": "Thu, 21 Mar 2024 10:00:00 PDT"}, {"title": "tvOS 17.4 (21L227)", "link": "https://developer.apple.com/news/releases/?id=03072024c", "published": "Thu, 07 Mar 2024 09:00:00 PST"}, {"title": "watchOS 10.4 (21T216)", "link": "https://developer.apple.com/news/releases/?id=03072024a", "published": "Thu, 07 Mar 2024 09:00:00 PST"}, {"title": "iOS 15.8.2 (19H384)", "link": "https://developer.apple.com/news/releases/?id=03052024b", "published": "Tue, 05 Mar 2024 09:00:00 PST"}, {"title": "iPadOS 15.8.2 (19H384)", "link": "https://developer.apple.com/news/releases/?id=03052024a", "published": "Tue, 05 Mar 2024 09:00:00 PST"}]}